{
	"animations": [
		{
			"loop": true,
			"offsets": [
				966,
				600
			],
			"anim": "idle",
			"fps": 18,
			"name": "Beef_assets idle",
			"indices": []
		},
		{
			"loop": false,
			"offsets": [
				964,
				601
			],
			"anim": "singDOWN",
			"fps": 13,
			"name": "Beef_assets down",
			"indices": []
		},
		{
			"loop": false,
			"offsets": [
				965,
				600
			],
			"anim": "singUP",
			"fps": 13,
			"name": "Beef_assets up",
			"indices": []
		},
		{
			"loop": false,
			"offsets": [
				967,
				600
			],
			"anim": "singRIGHT",
			"fps": 13,
			"name": "Beef_assets right",
			"indices": []
		},
		{
			"loop": true,
			"offsets": [
				969,
				601
			],
			"anim": "what",
			"fps": 18,
			"name": "Beef_assets GUH",
			"indices": []
		},
		{
			"loop": false,
			"offsets": [
				964,
				600
			],
			"anim": "singLEFT",
			"fps": 13,
			"name": "Beef_assets left",
			"indices": []
		},
		{
			"loop": false,
			"offsets": [
				1246,
				598
			],
			"anim": "singDOWNmiss",
			"fps": 13,
			"name": "Beef_assets th",
			"indices": []
		},
		{
			"loop": false,
			"offsets": [
				1251,
				600
			],
			"anim": "singLEFTmiss",
			"fps": 13,
			"name": "Beef_assets a",
			"indices": []
		},
		{
			"loop": false,
			"offsets": [
				1245,
				600
			],
			"anim": "singUPmiss",
			"fps": 13,
			"name": "Beef_assets f",
			"indices": []
		},
		{
			"loop": false,
			"offsets": [
				1248,
				602
			],
			"anim": "singRIGHTmiss",
			"fps": 13,
			"name": "Beef_assets wh",
			"indices": []
		}
	],
	"no_antialiasing": true,
	"image": "characters/Beef_assets",
	"position": [
		0,
		350
	],
	"healthicon": "minibeef",
	"flip_x": false,
	"healthbar_colors": [
		0,
		162,
		232
	],
	"camera_position": [
		940,
		-510
	],
	"sing_duration": 4,
	"scale": 1
}